[{"categories":[],"content":" Dependancies  https://podman.io/     Distrobox https://github.com/89luca89/distrobox  1 2distrobox-create --name dev-env-ubuntu-20 --image ubuntu:20.04 3 4distrobox-enter --name dev-env-ubuntu-20 5 6su - 7 8apt install vscode 9 10exit 11 12distrobox-create --name \u0026lt;cloned\u0026gt; --clone dev-env-ubuntu-20 13 14## save container as a image 15podman container commit \u0026lt;container-id\u0026gt; \u0026lt;image-name\u0026gt; 16 17podman save image-name | xz -T0 -c images.txz 18 19podman load images.txz 20 21 Toolbox https://github.com/containers/toolbox  1 2\u0026lt;define your docjer file\u0026gt; 3podman build . -t my-image-name 4toolbox create -i imagename 5toolbox enter imagename 6toolbox list 7# backup and restore 8podman container commit -p \u0026lt;container id\u0026gt; \u0026lt;img name\u0026gt; 9 10toolbox create --container go --image localhost/go-backup:latest 11podman save -o img.tar image-name 12 ","date":"Jan 10, 2022","img":"","permalink":"/posts/docker-development-env/","series":null,"tags":["docker"],"title":"Dockerize Devlopment Environment"},{"categories":[],"content":"Environment  Fedora Plasma  VScode  Docker   Backend Frameworks  Ruby on Rails  Elixir  Golang   Frontend Frameworks  VueJs  React  Tailwindcss   Communicatioin  Calendly  Discord  Slack   Web  Firefox  Brave  postman   Database  Postgresql  Redis  Elasticsearch  DBeaver  ","date":"Nov 2, 2021","img":"","permalink":"/posts/tools/","series":null,"tags":["Tech Stack"],"title":"My Favorite Tech Stack for 2022"},{"categories":null,"content":"","date":"Feb 28, 2019","img":"","permalink":"/about/","series":null,"tags":null,"title":"About"},{"categories":[],"content":"","date":"Feb 24, 2019","img":"/Screenshot-from-2019-02-24-12-25-57.png","permalink":"/posts/generator-pattern/","series":null,"tags":["Python"],"title":"Generator Pattern"},{"categories":[],"content":"","date":"Jan 31, 2019","img":"/Screenshot-from-2019-01-31-11-32-10.png","permalink":"/posts/functional-ruby/","series":null,"tags":["Ruby"],"title":"Functional Ruby"},{"categories":[],"content":"https://oshanz.github.io/til/ ","date":"Jan 5, 2019","img":"","permalink":"/posts/previous-blog/","series":null,"tags":[],"title":"Previous Blog"}]